keyman
