Metadata-Version: 1.1
Name: keyman
Version: 0.1.0rc19
Summary: A simple command-line password manager.
Home-page: UNKNOWN
Author: psrit
Author-email: xiaojx13@outlook.com
License: UNKNOWN
Platform: UNKNOWN
Classifier: Development Status :: 3 - Alpha
Classifier: Environment :: Console
Classifier: License :: OSI Approved :: Apache Software License
Classifier: Intended Audience :: Developers
Classifier: Operating System :: Microsoft :: Windows
Classifier: Operating System :: Unix
Classifier: Programming Language :: Python
Classifier: Topic :: Database
